paperreview/__init__.py
paperreview/__main__.py
paperreview/cli.py
paperreview/constants.py
paperreview/helper.py
paperreview-0.1.0.dist-info/LICENSE
paperreview-0.1.0.dist-info/METADATA
paperreview-0.1.0.dist-info/WHEEL
paperreview-0.1.0.dist-info/entry_points.txt
paperreview-0.1.0.dist-info/top_level.txt
paperreview-0.1.0.dist-info/RECORD
