Metadata-Version: 2.1
Name: paperreview
Version: 0.1.0
Summary: Awesome paperreview created by AdityaNG
Home-page: https://github.com/AdityaNG/PaperReview/
Author: AdityaNG
License-File: LICENSE
Requires-Dist: pypdf ==3.15.0
Requires-Dist: openai ==0.27.8
Requires-Dist: tqdm ==4.65.0
Requires-Dist: tiktoken ==0.4.0
Provides-Extra: test
Requires-Dist: pytest ; extra == 'test'
Requires-Dist: coverage ; extra == 'test'
Requires-Dist: flake8 ; extra == 'test'
Requires-Dist: black ; extra == 'test'
Requires-Dist: isort ; extra == 'test'
Requires-Dist: pytest-cov ; extra == 'test'
Requires-Dist: mypy ; extra == 'test'
Requires-Dist: gitchangelog ; extra == 'test'
Requires-Dist: mkdocs ; extra == 'test'
Requires-Dist: lark ==1.1.7 ; extra == 'test'
Requires-Dist: types-requests ==2.31.0.2 ; extra == 'test'
